py_audio2face/__init__.py
py_audio2face/audio2face.py
py_audio2face/settings.py
py_audio2face/utils.py
py_audio2face/assets/mark_arkit_solved_default.usd
py_audio2face/assets/mark_arkit_solved_streaming.usd
py_audio2face/modules/__init__.py
py_audio2face/modules/_audio2emotion.py
py_audio2face/modules/_export.py
py_audio2face/modules/_general.py
py_audio2face/modules/_player.py
py_audio2face/modules/_streaming.py
py_audio2face/modules/clients/__init__.py
py_audio2face/modules/clients/_http_client.py
py_audio2face/modules/clients/grpc_stub/__init__.py
py_audio2face/modules/clients/grpc_stub/audio2face_pb2.py
py_audio2face/modules/clients/grpc_stub/audio2face_pb2_grpc.py
py_audio2face-0.1.3.dist-info/LICENSE
py_audio2face-0.1.3.dist-info/METADATA
py_audio2face-0.1.3.dist-info/WHEEL
py_audio2face-0.1.3.dist-info/top_level.txt
py_audio2face-0.1.3.dist-info/RECORD
