Metadata-Version: 2.1
Name: py_audio2face
Version: 0.1.3
Summary: Generate expressive facial animation from audio. Animate 3D characters including lip, face, and emotions with audio-to-animation. 
Author: SocAIty
License: GPLv3
Project-URL: Repository, https://github.com/SocAIty/py_audio2face
Requires-Python: >=3.8
License-File: LICENSE
Requires-Dist: requests
Requires-Dist: tqdm
Requires-Dist: importlib-resources
Provides-Extra: streaming
Requires-Dist: numpy >=1.9.0 ; extra == 'streaming'
Requires-Dist: grpcio >=1.65.0 ; extra == 'streaming'
Requires-Dist: protobuf ==3.20.3 ; extra == 'streaming'
